{
  "functions" : [
    {
      "function" : "StringCchCopy",
      "file" : "/home/m2024-djj/Vulrag/rag/test_data_secvul/novul/ExtractToTempDirectory.c",
      "id" : "io.shiftleft.codepropertygraph.generated.nodes.Method[label=METHOD; id=1000100]",
      "AST" : [
        {
          "id" : "io.shiftleft.codepropertygraph.generated.nodes.MethodParameterIn[label=METHOD_PARAMETER_IN; id=1000101]",
          "edges" : [
            {
              "id" : "io.shiftleft.codepropertygraph.generated.edges.Ast@3b23b202",
              "in" : "io.shiftleft.codepropertygraph.generated.nodes.MethodParameterIn[label=METHOD_PARAMETER_IN; id=1000101]",
              "out" : "io.shiftleft.codepropertygraph.generated.nodes.Method[label=METHOD; id=1000100]"
            }
          ],
          "properties" : [
            {
              "key" : "ORDER",
              "value" : "1"
            },
            {
              "key" : "CODE",
              "value" : "szTempDir"
            },
            {
              "key" : "COLUMN_NUMBER",
              "value" : "22"
            },
            {
              "key" : "LINE_NUMBER",
              "value" : "22"
            },
            {
              "key" : "TYPE_FULL_NAME",
              "value" : "szTempDir"
            },
            {
              "key" : "EVALUATION_STRATEGY",
              "value" : "BY_VALUE"
            },
            {
              "key" : "NAME",
              "value" : "<anonymous>"
            }
          ]
        },
        {
          "id" : "io.shiftleft.codepropertygraph.generated.nodes.MethodParameterIn[label=METHOD_PARAMETER_IN; id=1000102]",
          "edges" : [
            {
              "id" : "io.shiftleft.codepropertygraph.generated.edges.Ast@3b23b5c3",
              "in" : "io.shiftleft.codepropertygraph.generated.nodes.MethodParameterIn[label=METHOD_PARAMETER_IN; id=1000102]",
              "out" : "io.shiftleft.codepropertygraph.generated.nodes.Method[label=METHOD; id=1000100]"
            }
          ],
          "properties" : [
            {
              "key" : "ORDER",
              "value" : "2"
            },
            {
              "key" : "CODE",
              "value" : "cchTempDirBuf"
            },
            {
              "key" : "COLUMN_NUMBER",
              "value" : "33"
            },
            {
              "key" : "LINE_NUMBER",
              "value" : "22"
            },
            {
              "key" : "TYPE_FULL_NAME",
              "value" : "cchTempDirBuf"
            },
            {
              "key" : "EVALUATION_STRATEGY",
              "value" : "BY_VALUE"
            },
            {
              "key" : "NAME",
              "value" : "<anonymous>"
            }
          ]
        },
        {
          "id" : "io.shiftleft.codepropertygraph.generated.nodes.MethodParameterIn[label=METHOD_PARAMETER_IN; id=1000103]",
          "edges" : [
            {
              "id" : "io.shiftleft.codepropertygraph.generated.edges.Ast@3b23b984",
              "in" : "io.shiftleft.codepropertygraph.generated.nodes.MethodParameterIn[label=METHOD_PARAMETER_IN; id=1000103]",
              "out" : "io.shiftleft.codepropertygraph.generated.nodes.Method[label=METHOD; id=1000100]"
            }
          ],
          "properties" : [
            {
              "key" : "ORDER",
              "value" : "3"
            },
            {
              "key" : "CODE",
              "value" : "szModule"
            },
            {
              "key" : "COLUMN_NUMBER",
              "value" : "48"
            },
            {
              "key" : "LINE_NUMBER",
              "value" : "22"
            },
            {
              "key" : "TYPE_FULL_NAME",
              "value" : "szModule"
            },
            {
              "key" : "EVALUATION_STRATEGY",
              "value" : "BY_VALUE"
            },
            {
              "key" : "NAME",
              "value" : "<anonymous>"
            }
          ]
        },
        {
          "id" : "io.shiftleft.codepropertygraph.generated.nodes.Block[label=BLOCK; id=1000104]",
          "edges" : [
            {
              "id" : "io.shiftleft.codepropertygraph.generated.edges.Ast@3b23bd45",
              "in" : "io.shiftleft.codepropertygraph.generated.nodes.Block[label=BLOCK; id=1000104]",
              "out" : "io.shiftleft.codepropertygraph.generated.nodes.Method[label=METHOD; id=1000100]"
            }
          ],
          "properties" : [
            {
              "key" : "TYPE_FULL_NAME",
              "value" : "void"
            },
            {
              "key" : "ORDER",
              "value" : "4"
            },
            {
              "key" : "ARGUMENT_INDEX",
              "value" : "4"
            },
            {
              "key" : "CODE",
              "value" : ""
            }
          ]
        },
        {
          "id" : "io.shiftleft.codepropertygraph.generated.nodes.MethodReturn[label=METHOD_RETURN; id=1000105]",
          "edges" : [
            {
              "id" : "io.shiftleft.codepropertygraph.generated.edges.Ast@3b23c106",
              "in" : "io.shiftleft.codepropertygraph.generated.nodes.MethodReturn[label=METHOD_RETURN; id=1000105]",
              "out" : "io.shiftleft.codepropertygraph.generated.nodes.Method[label=METHOD; id=1000100]"
            },
            {
              "id" : "io.shiftleft.codepropertygraph.generated.edges.Cfg@3b23c6e8",
              "in" : "io.shiftleft.codepropertygraph.generated.nodes.MethodReturn[label=METHOD_RETURN; id=1000105]",
              "out" : "io.shiftleft.codepropertygraph.generated.nodes.Method[label=METHOD; id=1000100]"
            }
          ],
          "properties" : [
            {
              "key" : "ORDER",
              "value" : "5"
            },
            {
              "key" : "LINE_NUMBER",
              "value" : "22"
            },
            {
              "key" : "TYPE_FULL_NAME",
              "value" : "int"
            },
            {
              "key" : "CODE",
              "value" : "RET"
            },
            {
              "key" : "EVALUATION_STRATEGY",
              "value" : "BY_VALUE"
            },
            {
              "key" : "COLUMN_NUMBER",
              "value" : "8"
            }
          ]
        },
        {
          "id" : "io.shiftleft.codepropertygraph.generated.nodes.MethodParameterOut[label=METHOD_PARAMETER_OUT; id=1000122]",
          "edges" : [
            {
              "id" : "io.shiftleft.codepropertygraph.generated.edges.Ast@3b2400d7",
              "in" : "io.shiftleft.codepropertygraph.generated.nodes.MethodParameterOut[label=METHOD_PARAMETER_OUT; id=1000122]",
              "out" : "io.shiftleft.codepropertygraph.generated.nodes.Method[label=METHOD; id=1000100]"
            }
          ],
          "properties" : [
            {
              "key" : "ORDER",
              "value" : "1"
            },
            {
              "key" : "CODE",
              "value" : "szTempDir"
            },
            {
              "key" : "COLUMN_NUMBER",
              "value" : "22"
            },
            {
              "key" : "LINE_NUMBER",
              "value" : "22"
            },
            {
              "key" : "TYPE_FULL_NAME",
              "value" : "szTempDir"
            },
            {
              "key" : "EVALUATION_STRATEGY",
              "value" : "BY_VALUE"
            },
            {
              "key" : "NAME",
              "value" : "<anonymous>"
            }
          ]
        },
        {
          "id" : "io.shiftleft.codepropertygraph.generated.nodes.MethodParameterOut[label=METHOD_PARAMETER_OUT; id=1000123]",
          "edges" : [
            {
              "id" : "io.shiftleft.codepropertygraph.generated.edges.Ast@3b240498",
              "in" : "io.shiftleft.codepropertygraph.generated.nodes.MethodParameterOut[label=METHOD_PARAMETER_OUT; id=1000123]",
              "out" : "io.shiftleft.codepropertygraph.generated.nodes.Method[label=METHOD; id=1000100]"
            }
          ],
          "properties" : [
            {
              "key" : "ORDER",
              "value" : "2"
            },
            {
              "key" : "CODE",
              "value" : "cchTempDirBuf"
            },
            {
              "key" : "COLUMN_NUMBER",
              "value" : "33"
            },
            {
              "key" : "LINE_NUMBER",
              "value" : "22"
            },
            {
              "key" : "TYPE_FULL_NAME",
              "value" : "cchTempDirBuf"
            },
            {
              "key" : "EVALUATION_STRATEGY",
              "value" : "BY_VALUE"
            },
            {
              "key" : "NAME",
              "value" : "<anonymous>"
            }
          ]
        },
        {
          "id" : "io.shiftleft.codepropertygraph.generated.nodes.MethodParameterOut[label=METHOD_PARAMETER_OUT; id=1000124]",
          "edges" : [
            {
              "id" : "io.shiftleft.codepropertygraph.generated.edges.Ast@3b240859",
              "in" : "io.shiftleft.codepropertygraph.generated.nodes.MethodParameterOut[label=METHOD_PARAMETER_OUT; id=1000124]",
              "out" : "io.shiftleft.codepropertygraph.generated.nodes.Method[label=METHOD; id=1000100]"
            }
          ],
          "properties" : [
            {
              "key" : "ORDER",
              "value" : "3"
            },
            {
              "key" : "CODE",
              "value" : "szModule"
            },
            {
              "key" : "COLUMN_NUMBER",
              "value" : "48"
            },
            {
              "key" : "LINE_NUMBER",
              "value" : "22"
            },
            {
              "key" : "TYPE_FULL_NAME",
              "value" : "szModule"
            },
            {
              "key" : "EVALUATION_STRATEGY",
              "value" : "BY_VALUE"
            },
            {
              "key" : "NAME",
              "value" : "<anonymous>"
            }
          ]
        }
      ],
      "CFG" : [
        {
          "id" : "io.shiftleft.codepropertygraph.generated.nodes.Block[label=BLOCK; id=1000104]",
          "edges" : [
            {
              "id" : "io.shiftleft.codepropertygraph.generated.edges.Ast@3b23bd45",
              "in" : "io.shiftleft.codepropertygraph.generated.nodes.Block[label=BLOCK; id=1000104]",
              "out" : "io.shiftleft.codepropertygraph.generated.nodes.Method[label=METHOD; id=1000100]"
            }
          ],
          "properties" : [
            {
              "key" : "TYPE_FULL_NAME",
              "value" : "void"
            },
            {
              "key" : "ORDER",
              "value" : "4"
            },
            {
              "key" : "ARGUMENT_INDEX",
              "value" : "4"
            },
            {
              "key" : "CODE",
              "value" : ""
            }
          ]
        }
      ],
      "PDG" : [
      ]
    },
    {
      "function" : "CreateDirectory",
      "file" : "/home/m2024-djj/Vulrag/rag/test_data_secvul/novul/ExtractToTempDirectory.c",
      "id" : "io.shiftleft.codepropertygraph.generated.nodes.Method[label=METHOD; id=1000106]",
      "AST" : [
        {
          "id" : "io.shiftleft.codepropertygraph.generated.nodes.MethodParameterIn[label=METHOD_PARAMETER_IN; id=1000107]",
          "edges" : [
            {
              "id" : "io.shiftleft.codepropertygraph.generated.edges.Ast@3b23c942",
              "in" : "io.shiftleft.codepropertygraph.generated.nodes.MethodParameterIn[label=METHOD_PARAMETER_IN; id=1000107]",
              "out" : "io.shiftleft.codepropertygraph.generated.nodes.Method[label=METHOD; id=1000106]"
            }
          ],
          "properties" : [
            {
              "key" : "ORDER",
              "value" : "1"
            },
            {
              "key" : "CODE",
              "value" : "szTempDir"
            },
            {
              "key" : "COLUMN_NUMBER",
              "value" : "54"
            },
            {
              "key" : "LINE_NUMBER",
              "value" : "30"
            },
            {
              "key" : "TYPE_FULL_NAME",
              "value" : "szTempDir"
            },
            {
              "key" : "EVALUATION_STRATEGY",
              "value" : "BY_VALUE"
            },
            {
              "key" : "NAME",
              "value" : "<anonymous>"
            }
          ]
        },
        {
          "id" : "io.shiftleft.codepropertygraph.generated.nodes.MethodParameterIn[label=METHOD_PARAMETER_IN; id=1000108]",
          "edges" : [
            {
              "id" : "io.shiftleft.codepropertygraph.generated.edges.Ast@3b23cd03",
              "in" : "io.shiftleft.codepropertygraph.generated.nodes.MethodParameterIn[label=METHOD_PARAMETER_IN; id=1000108]",
              "out" : "io.shiftleft.codepropertygraph.generated.nodes.Method[label=METHOD; id=1000106]"
            }
          ],
          "properties" : [
            {
              "key" : "ORDER",
              "value" : "2"
            },
            {
              "key" : "CODE",
              "value" : "NULL"
            },
            {
              "key" : "COLUMN_NUMBER",
              "value" : "65"
            },
            {
              "key" : "LINE_NUMBER",
              "value" : "30"
            },
            {
              "key" : "TYPE_FULL_NAME",
              "value" : "NULL"
            },
            {
              "key" : "EVALUATION_STRATEGY",
              "value" : "BY_VALUE"
            },
            {
              "key" : "NAME",
              "value" : "<anonymous>"
            }
          ]
        },
        {
          "id" : "io.shiftleft.codepropertygraph.generated.nodes.Block[label=BLOCK; id=1000109]",
          "edges" : [
            {
              "id" : "io.shiftleft.codepropertygraph.generated.edges.Ast@3b23d0c4",
              "in" : "io.shiftleft.codepropertygraph.generated.nodes.Block[label=BLOCK; id=1000109]",
              "out" : "io.shiftleft.codepropertygraph.generated.nodes.Method[label=METHOD; id=1000106]"
            }
          ],
          "properties" : [
            {
              "key" : "TYPE_FULL_NAME",
              "value" : "void"
            },
            {
              "key" : "ORDER",
              "value" : "3"
            },
            {
              "key" : "ARGUMENT_INDEX",
              "value" : "3"
            },
            {
              "key" : "CODE",
              "value" : ""
            }
          ]
        },
        {
          "id" : "io.shiftleft.codepropertygraph.generated.nodes.MethodReturn[label=METHOD_RETURN; id=1000110]",
          "edges" : [
            {
              "id" : "io.shiftleft.codepropertygraph.generated.edges.Ast@3b23d485",
              "in" : "io.shiftleft.codepropertygraph.generated.nodes.MethodReturn[label=METHOD_RETURN; id=1000110]",
              "out" : "io.shiftleft.codepropertygraph.generated.nodes.Method[label=METHOD; id=1000106]"
            },
            {
              "id" : "io.shiftleft.codepropertygraph.generated.edges.Cfg@3b23da67",
              "in" : "io.shiftleft.codepropertygraph.generated.nodes.MethodReturn[label=METHOD_RETURN; id=1000110]",
              "out" : "io.shiftleft.codepropertygraph.generated.nodes.Method[label=METHOD; id=1000106]"
            }
          ],
          "properties" : [
            {
              "key" : "ORDER",
              "value" : "4"
            },
            {
              "key" : "LINE_NUMBER",
              "value" : "30"
            },
            {
              "key" : "TYPE_FULL_NAME",
              "value" : "int"
            },
            {
              "key" : "CODE",
              "value" : "RET"
            },
            {
              "key" : "EVALUATION_STRATEGY",
              "value" : "BY_VALUE"
            },
            {
              "key" : "COLUMN_NUMBER",
              "value" : "38"
            }
          ]
        },
        {
          "id" : "io.shiftleft.codepropertygraph.generated.nodes.MethodParameterOut[label=METHOD_PARAMETER_OUT; id=1000125]",
          "edges" : [
            {
              "id" : "io.shiftleft.codepropertygraph.generated.edges.Ast@3b240cd4",
              "in" : "io.shiftleft.codepropertygraph.generated.nodes.MethodParameterOut[label=METHOD_PARAMETER_OUT; id=1000125]",
              "out" : "io.shiftleft.codepropertygraph.generated.nodes.Method[label=METHOD; id=1000106]"
            }
          ],
          "properties" : [
            {
              "key" : "ORDER",
              "value" : "1"
            },
            {
              "key" : "CODE",
              "value" : "szTempDir"
            },
            {
              "key" : "COLUMN_NUMBER",
              "value" : "54"
            },
            {
              "key" : "LINE_NUMBER",
              "value" : "30"
            },
            {
              "key" : "TYPE_FULL_NAME",
              "value" : "szTempDir"
            },
            {
              "key" : "EVALUATION_STRATEGY",
              "value" : "BY_VALUE"
            },
            {
              "key" : "NAME",
              "value" : "<anonymous>"
            }
          ]
        },
        {
          "id" : "io.shiftleft.codepropertygraph.generated.nodes.MethodParameterOut[label=METHOD_PARAMETER_OUT; id=1000126]",
          "edges" : [
            {
              "id" : "io.shiftleft.codepropertygraph.generated.edges.Ast@3b241095",
              "in" : "io.shiftleft.codepropertygraph.generated.nodes.MethodParameterOut[label=METHOD_PARAMETER_OUT; id=1000126]",
              "out" : "io.shiftleft.codepropertygraph.generated.nodes.Method[label=METHOD; id=1000106]"
            }
          ],
          "properties" : [
            {
              "key" : "ORDER",
              "value" : "2"
            },
            {
              "key" : "CODE",
              "value" : "NULL"
            },
            {
              "key" : "COLUMN_NUMBER",
              "value" : "65"
            },
            {
              "key" : "LINE_NUMBER",
              "value" : "30"
            },
            {
              "key" : "TYPE_FULL_NAME",
              "value" : "NULL"
            },
            {
              "key" : "EVALUATION_STRATEGY",
              "value" : "BY_VALUE"
            },
            {
              "key" : "NAME",
              "value" : "<anonymous>"
            }
          ]
        }
      ],
      "CFG" : [
        {
          "id" : "io.shiftleft.codepropertygraph.generated.nodes.Block[label=BLOCK; id=1000109]",
          "edges" : [
            {
              "id" : "io.shiftleft.codepropertygraph.generated.edges.Ast@3b23d0c4",
              "in" : "io.shiftleft.codepropertygraph.generated.nodes.Block[label=BLOCK; id=1000109]",
              "out" : "io.shiftleft.codepropertygraph.generated.nodes.Method[label=METHOD; id=1000106]"
            }
          ],
          "properties" : [
            {
              "key" : "TYPE_FULL_NAME",
              "value" : "void"
            },
            {
              "key" : "ORDER",
              "value" : "3"
            },
            {
              "key" : "ARGUMENT_INDEX",
              "value" : "3"
            },
            {
              "key" : "CODE",
              "value" : ""
            }
          ]
        }
      ],
      "PDG" : [
      ]
    },
    {
      "function" : "DeleteDirectory",
      "file" : "/home/m2024-djj/Vulrag/rag/test_data_secvul/novul/ExtractToTempDirectory.c",
      "id" : "io.shiftleft.codepropertygraph.generated.nodes.Method[label=METHOD; id=1000111]",
      "AST" : [
        {
          "id" : "io.shiftleft.codepropertygraph.generated.nodes.MethodParameterIn[label=METHOD_PARAMETER_IN; id=1000112]",
          "edges" : [
            {
              "id" : "io.shiftleft.codepropertygraph.generated.edges.Ast@3b23dca2",
              "in" : "io.shiftleft.codepropertygraph.generated.nodes.MethodParameterIn[label=METHOD_PARAMETER_IN; id=1000112]",
              "out" : "io.shiftleft.codepropertygraph.generated.nodes.Method[label=METHOD; id=1000111]"
            }
          ],
          "properties" : [
            {
              "key" : "ORDER",
              "value" : "1"
            },
            {
              "key" : "CODE",
              "value" : "szTempDir"
            },
            {
              "key" : "COLUMN_NUMBER",
              "value" : "32"
            },
            {
              "key" : "LINE_NUMBER",
              "value" : "44"
            },
            {
              "key" : "TYPE_FULL_NAME",
              "value" : "szTempDir"
            },
            {
              "key" : "EVALUATION_STRATEGY",
              "value" : "BY_VALUE"
            },
            {
              "key" : "NAME",
              "value" : "<anonymous>"
            }
          ]
        },
        {
          "id" : "io.shiftleft.codepropertygraph.generated.nodes.Block[label=BLOCK; id=1000113]",
          "edges" : [
            {
              "id" : "io.shiftleft.codepropertygraph.generated.edges.Ast@3b23e063",
              "in" : "io.shiftleft.codepropertygraph.generated.nodes.Block[label=BLOCK; id=1000113]",
              "out" : "io.shiftleft.codepropertygraph.generated.nodes.Method[label=METHOD; id=1000111]"
            }
          ],
          "properties" : [
            {
              "key" : "TYPE_FULL_NAME",
              "value" : "void"
            },
            {
              "key" : "ORDER",
              "value" : "2"
            },
            {
              "key" : "ARGUMENT_INDEX",
              "value" : "2"
            },
            {
              "key" : "CODE",
              "value" : ""
            }
          ]
        },
        {
          "id" : "io.shiftleft.codepropertygraph.generated.nodes.MethodReturn[label=METHOD_RETURN; id=1000114]",
          "edges" : [
            {
              "id" : "io.shiftleft.codepropertygraph.generated.edges.Ast@3b23e424",
              "in" : "io.shiftleft.codepropertygraph.generated.nodes.MethodReturn[label=METHOD_RETURN; id=1000114]",
              "out" : "io.shiftleft.codepropertygraph.generated.nodes.Method[label=METHOD; id=1000111]"
            },
            {
              "id" : "io.shiftleft.codepropertygraph.generated.edges.Cfg@3b23ea06",
              "in" : "io.shiftleft.codepropertygraph.generated.nodes.MethodReturn[label=METHOD_RETURN; id=1000114]",
              "out" : "io.shiftleft.codepropertygraph.generated.nodes.Method[label=METHOD; id=1000111]"
            }
          ],
          "properties" : [
            {
              "key" : "ORDER",
              "value" : "3"
            },
            {
              "key" : "LINE_NUMBER",
              "value" : "44"
            },
            {
              "key" : "TYPE_FULL_NAME",
              "value" : "int"
            },
            {
              "key" : "CODE",
              "value" : "RET"
            },
            {
              "key" : "EVALUATION_STRATEGY",
              "value" : "BY_VALUE"
            },
            {
              "key" : "COLUMN_NUMBER",
              "value" : "16"
            }
          ]
        },
        {
          "id" : "io.shiftleft.codepropertygraph.generated.nodes.MethodParameterOut[label=METHOD_PARAMETER_OUT; id=1000127]",
          "edges" : [
            {
              "id" : "io.shiftleft.codepropertygraph.generated.edges.Ast@3b2414f1",
              "in" : "io.shiftleft.codepropertygraph.generated.nodes.MethodParameterOut[label=METHOD_PARAMETER_OUT; id=1000127]",
              "out" : "io.shiftleft.codepropertygraph.generated.nodes.Method[label=METHOD; id=1000111]"
            }
          ],
          "properties" : [
            {
              "key" : "ORDER",
              "value" : "1"
            },
            {
              "key" : "CODE",
              "value" : "szTempDir"
            },
            {
              "key" : "COLUMN_NUMBER",
              "value" : "32"
            },
            {
              "key" : "LINE_NUMBER",
              "value" : "44"
            },
            {
              "key" : "TYPE_FULL_NAME",
              "value" : "szTempDir"
            },
            {
              "key" : "EVALUATION_STRATEGY",
              "value" : "BY_VALUE"
            },
            {
              "key" : "NAME",
              "value" : "<anonymous>"
            }
          ]
        }
      ],
      "CFG" : [
        {
          "id" : "io.shiftleft.codepropertygraph.generated.nodes.Block[label=BLOCK; id=1000113]",
          "edges" : [
            {
              "id" : "io.shiftleft.codepropertygraph.generated.edges.Ast@3b23e063",
              "in" : "io.shiftleft.codepropertygraph.generated.nodes.Block[label=BLOCK; id=1000113]",
              "out" : "io.shiftleft.codepropertygraph.generated.nodes.Method[label=METHOD; id=1000111]"
            }
          ],
          "properties" : [
            {
              "key" : "TYPE_FULL_NAME",
              "value" : "void"
            },
            {
              "key" : "ORDER",
              "value" : "2"
            },
            {
              "key" : "ARGUMENT_INDEX",
              "value" : "2"
            },
            {
              "key" : "CODE",
              "value" : ""
            }
          ]
        }
      ],
      "PDG" : [
      ]
    }
  ]
}